drsDistributions/Binomialdistribution.py
drsDistributions/Gaussiandistribution.py
drsDistributions/Generaldistribution.py
drsDistributions/__init__.py
drsDistributions-0.1.dist-info/DESCRIPTION.rst
drsDistributions-0.1.dist-info/METADATA
drsDistributions-0.1.dist-info/RECORD
drsDistributions-0.1.dist-info/WHEEL
drsDistributions-0.1.dist-info/metadata.json
drsDistributions-0.1.dist-info/top_level.txt
