Metadata-Version: 2.0
Name: drsDistributions
Version: 0.1
Summary: Package to deal with probability distributions
Home-page: UNKNOWN
Author: UNKNOWN
Author-email: UNKNOWN
License: UNKNOWN
Platform: UNKNOWN
